dfs_sdk/__init__.py
dfs_sdk/api.py
dfs_sdk/base.py
dfs_sdk/connection.py
dfs_sdk/constants.py
dfs_sdk/context.py
dfs_sdk/dat_jank.py
dfs_sdk/dlogging.py
dfs_sdk/exceptions.py
dfs_sdk/scaffold.py
dfs_sdk/hooks/__init__.py
dfs_sdk/hooks/base.py
dfs_sdk/hooks/cleanup.py
dfs_sdk/log_cfg/debug_logging.json
dfs_sdk/log_cfg/error_logging.json
dfs_sdk/log_cfg/info_logging.json
dfs_sdk/schema/__init__.py
dfs_sdk/schema/reader.py
dfs_sdk-1.2.27.dist-info/COPYING
dfs_sdk-1.2.27.dist-info/METADATA
dfs_sdk-1.2.27.dist-info/WHEEL
dfs_sdk-1.2.27.dist-info/top_level.txt
dfs_sdk-1.2.27.dist-info/RECORD
