Metadata-Version: 2.1
Name: dfs-sdk
Version: 1.2.27
Summary: Datera Fabric Python SDK
Home-page: https://github.com/Datera/python-sdk/
Author: Datera Automation Team
Author-email: support@datera.io
License: UNKNOWN
Download-URL: https://github.com/Datera/python-sdk/tarball/v1.2.27
Platform: UNKNOWN
Classifier: Programming Language :: Python :: 2
Classifier: Programming Language :: Python :: 3
Classifier: License :: OSI Approved :: Apache Software License
Classifier: Operating System :: OS Independent
Requires-Dist: requests
Requires-Dist: six
Requires-Dist: urllib3
